funktion/__init__.py
funktion-0.1.0.dist-info/LICENSE
funktion-0.1.0.dist-info/WHEEL
funktion-0.1.0.dist-info/METADATA
funktion-0.1.0.dist-info/RECORD
